confiture/__init__.py
confiture/_core.cp312-win_amd64.pyd
confiture/cli/__init__.py
confiture/cli/branch.py
confiture/cli/coordinate.py
confiture/cli/dry_run.py
confiture/cli/generate.py
confiture/cli/git_validation.py
confiture/cli/lint_formatter.py
confiture/cli/main.py
confiture/cli/prep_seed_formatter.py
confiture/cli/seed.py
confiture/config/__init__.py
confiture/config/environment.py
confiture/core/__init__.py
confiture/core/anonymization/__init__.py
confiture/core/anonymization/audit.py
confiture/core/anonymization/benchmarking.py
confiture/core/anonymization/breach_notification.py
confiture/core/anonymization/compliance.py
confiture/core/anonymization/composer.py
confiture/core/anonymization/data_subject_rights.py
confiture/core/anonymization/factory.py
confiture/core/anonymization/governance.py
confiture/core/anonymization/performance.py
confiture/core/anonymization/profile.py
confiture/core/anonymization/registry.py
confiture/core/anonymization/security/kms_manager.py
confiture/core/anonymization/security/lineage.py
confiture/core/anonymization/security/token_store.py
confiture/core/anonymization/strategies/__init__.py
confiture/core/anonymization/strategies/address.py
confiture/core/anonymization/strategies/credit_card.py
confiture/core/anonymization/strategies/custom.py
confiture/core/anonymization/strategies/date.py
confiture/core/anonymization/strategies/differential_privacy.py
confiture/core/anonymization/strategies/email.py
confiture/core/anonymization/strategies/format_preserving_encryption.py
confiture/core/anonymization/strategies/hash.py
confiture/core/anonymization/strategies/ip_address.py
confiture/core/anonymization/strategies/masking_retention.py
confiture/core/anonymization/strategies/name.py
confiture/core/anonymization/strategies/phone.py
confiture/core/anonymization/strategies/preserve.py
confiture/core/anonymization/strategies/redact.py
confiture/core/anonymization/strategies/salted_hashing.py
fraiseql_confiture-0.3.13.dist-info/METADATA
fraiseql_confiture-0.3.13.dist-info/WHEEL
fraiseql_confiture-0.3.13.dist-info/entry_points.txt
fraiseql_confiture-0.3.13.dist-info/licenses/LICENSE
fraiseql_confiture-0.3.13.dist-info/RECORD
