Metadata-Version: 2.4
Name: fraiseql-confiture
Version: 0.3.13
Classifier: Development Status :: 4 - Beta
Classifier: Intended Audience :: Developers
Classifier: License :: OSI Approved :: MIT License
Classifier: Programming Language :: Python :: 3
Classifier: Programming Language :: Python :: 3.11
Classifier: Programming Language :: Python :: 3.12
Classifier: Programming Language :: Python :: 3.13
Classifier: Topic :: Database
Classifier: Topic :: Software Development :: Libraries :: Python Modules
Classifier: Topic :: Software Development :: Version Control
Requires-Dist: typer>=0.12.0
Requires-Dist: rich>=13.7.0
Requires-Dist: pydantic>=2.5.0
Requires-Dist: pyyaml>=6.0.1
Requires-Dist: psycopg[binary,pool]>=3.1.0
Requires-Dist: sqlparse>=0.5.0
Requires-Dist: cryptography>=42.0.0
Requires-Dist: pytest>=8.0.0 ; extra == 'testing'
Requires-Dist: pytest-asyncio>=0.23.0 ; extra == 'testing'
Requires-Dist: pytest-cov>=4.1.0 ; extra == 'testing'
Requires-Dist: pytest-json-report>=1.5.0 ; extra == 'testing'
Requires-Dist: pytest>=8.0.0 ; extra == 'dev'
Requires-Dist: pytest-asyncio>=0.23.0 ; extra == 'dev'
Requires-Dist: pytest-cov>=4.1.0 ; extra == 'dev'
Requires-Dist: pytest-watch>=4.2.0 ; extra == 'dev'
Requires-Dist: pytest-json-report>=1.5.0 ; extra == 'dev'
Requires-Dist: ruff>=0.6.0 ; extra == 'dev'
Requires-Dist: ty>=0.0.7 ; extra == 'dev'
Requires-Dist: maturin>=1.7.0 ; extra == 'dev'
Provides-Extra: testing
Provides-Extra: dev
Provides-Extra: fraiseql
License-File: LICENSE
Summary: PostgreSQL schema evolution with built-in multi-agent coordination 🍓
Keywords: postgresql,migration,database,schema,ddl,coordination,multi-agent,collaboration,conflict-detection,ai-agents
Home-Page: https://github.com/fraiseql/confiture
Author-email: evoludigit <lionel.hamayon@evolution-digitale.fr>
License: MIT
Requires-Python: >=3.11
Project-URL: Homepage, https://github.com/fraiseql/confiture
Project-URL: Documentation, https://github.com/fraiseql/confiture
Project-URL: Repository, https://github.com/fraiseql/confiture
Project-URL: Issues, https://github.com/fraiseql/confiture/issues
Project-URL: FraiseQL, https://github.com/fraiseql/fraiseql
